aemo/__init__.py
aemo/key.py
aemo/tables/__init__.py
aemo/tables/settlements.py
aemo_EIGENMODE-0.1.20.dist-info/LICENSE
aemo_EIGENMODE-0.1.20.dist-info/METADATA
aemo_EIGENMODE-0.1.20.dist-info/WHEEL
aemo_EIGENMODE-0.1.20.dist-info/top_level.txt
aemo_EIGENMODE-0.1.20.dist-info/RECORD
