Metadata-Version: 2.1
Name: aemo-EIGENMODE
Version: 0.1.20
Summary: A package to parse and verify AEMO MMS data model files
Home-page: https://github.com/esheppa/aemo-py
Author: Eric Sheppard
Author-email: eric@eigenmo.de
License: UNKNOWN
Platform: UNKNOWN
Classifier: Programming Language :: Python :: 3
Classifier: License :: OSI Approved :: MIT License
Classifier: Operating System :: OS Independent
Requires-Python: >=3.8
